ddpitools/__init__.py
ddpitools/fonctions_dusage.py
ddpitools-0.3.3.dist-info/METADATA
ddpitools-0.3.3.dist-info/WHEEL
ddpitools-0.3.3.dist-info/licenses/LICENSE
ddpitools-0.3.3.dist-info/RECORD
