Metadata-Version: 2.4
Name: ddpitools
Version: 0.3.3
Summary: Ce package est conçu pour générer les fonctions de routine de DDPI. Il encapsule le développement pour faciliter l'utilisation des fonctions utiles.
Project-URL: Homepage, https://github.com/GuyNYAMSI/outilsddpi
Project-URL: Bug Tracker, https://github.com/GuyNYAMSI/ddpitools/issues
Author-email: GUY NYAMSI <nyamsguy@gmail.com>
License-File: LICENSE
Classifier: License :: OSI Approved :: MIT License
Classifier: Operating System :: OS Independent
Classifier: Programming Language :: Python :: 3
Requires-Python: >=3.9
Requires-Dist: datetime
Requires-Dist: openpyxl
Requires-Dist: requests
